xrf/__init__.py
xrf/base.py
xrf-0.1.1.dist-info/LICENSE
xrf-0.1.1.dist-info/METADATA
xrf-0.1.1.dist-info/WHEEL
xrf-0.1.1.dist-info/top_level.txt
xrf-0.1.1.dist-info/RECORD
