Metadata-Version: 2.1
Name: xrf
Version: 0.1.1
Summary: ExPLAINABLE rANDOM fORESTS (xrf)
Home-page: https://github.com/henrikbostrom/xrf
Author: Henrik Boström
Author-email: bostromh@kth.se
Project-URL: Bug Tracker, https://github.com//henrikbostrom/xrf/issues
Classifier: Programming Language :: Python :: 3
Classifier: License :: OSI Approved :: BSD License
Classifier: Operating System :: OS Independent
Requires-Python: >=3.8
License-File: LICENSE
Requires-Dist: numpy
Requires-Dist: pandas
Requires-Dist: scikit-learn
Requires-Dist: scipy
Requires-Dist: joblib
